ng2django/__init__.py
ng2django/__main__.py
ng2django/ng2django.py
ng2django-0.1.4.dist-info/LICENSE
ng2django-0.1.4.dist-info/METADATA
ng2django-0.1.4.dist-info/WHEEL
ng2django-0.1.4.dist-info/entry_points.txt
ng2django-0.1.4.dist-info/top_level.txt
ng2django-0.1.4.dist-info/RECORD
