Metadata-Version: 2.1
Name: ng2django
Version: 0.1.4
Summary: Convert your Angular built index.html file to Django Template syntax
Home-page: https://github.com/Hall-Erik/ng2django
Author: Erik Hall
Author-email: hall.erik@gmail.com
License: UNKNOWN
Platform: UNKNOWN
Classifier: Development Status :: 3 - Alpha
Classifier: Intended Audience :: Developers
Classifier: Topic :: Software Development :: Build Tools
Classifier: License :: OSI Approved :: MIT License
Classifier: Programming Language :: Python :: 3
Requires-Python: >=3.6
Requires-Dist: beautifulsoup4
